[
  { "file": "Abhogi - Pandit Hariprasad Chaurasia.mp3", "title": "Abhogi", "tags": [], "mood": [], "tempo": null, "key": null },
  { "file": "Al jbal li dargoug alliya - Release.mp3", "title": "Al jbal li dargoug alliya", "tags": [], "mood": [], "tempo": null, "key": null },
  { "file": "Alap in the Multani mode - Mohin ud din.mp3", "title": "Alap in the Multani mode", "tags": [], "mood": [], "tempo": null, "key": null },
  { "file": "Ali Farka Touré, Toumani Diabaté - Ruby - World Circuit Records.mp3", "title": "Ruby", "tags": [], "mood": [], "tempo": null, "key": null },
  { "file": "Ali Jihad Racy - The Land Of The Blessed - 0092julian.mp3", "title": "The Land Of The Blessed", "tags": [], "mood": [], "tempo": null, "key": null },
  { "file": "Amazigh Lullaby - Montserrat Figueras.mp3", "title": "Amazigh Lullaby", "tags": [], "mood": [], "tempo": null, "key": null },
  { "file": "Bezmârâ̂ - Ceng Taksimi [ Yitik Sesin Peşinde © 2000 Kalan Müzik ] - Kalan Müzik.mp3", "title": "Ceng Taksimi", "tags": [], "mood": [], "tempo": null, "key": null },
  { "file": "Bezmârâ̂ - Kürdi Peşrev [ Yitik Sesin Peşinde © 2000 Kalan Müzik ] - Kalan Müzik.mp3", "title": "Kürdi Peşrev", "tags": [], "mood": [], "tempo": null, "key": null },
  { "file": "Bezmârâ Topluluğu - Arazbar Peşrev (Fahte - Nefirî Behram)  Yitik Sesin Peşinde - Ferografik.mp3", "title": "Arazbar Peşrev", "tags": [], "mood": [], "tempo": null, "key": null },
  { "file": "Bezmârâ Topluluğu - Kanun Taksimi  Yitik Sesin Peşinde - Ferografik.mp3", "title": "Kanun Taksimi", "tags": [], "mood": [], "tempo": null, "key": null },
  { "file": "Bezmârâ Topluluğu - Çeng Taksimi  Yitik Sesin Peşinde - Ferografik.mp3", "title": "Çeng Taksimi", "tags": [], "mood": [], "tempo": null, "key": null },
  { "file": "Cambodia Traditional Music Vol. 2 Tribe Music, Folk Music and Popular Dances 1979 Folkways - Snows Ov Gethen.mp3", "title": "Cambodian Traditional Music", "tags": [], "mood": [], "tempo": null, "key": null },
  { "file": "Daramad - Parissa.mp3", "title": "Daramad", "tags": [], "mood": [], "tempo": null, "key": null },
  { "file": "Debussy. Preludios. Libro I. Preludio nº 6 Des pas sur la neige - Musicnetmaterials.mp3", "title": "Debussy - Des pas sur la neige", "tags": [], "mood": [], "tempo": null, "key": null },
  { "file": "Faramarz Payvar And Ensemble - Dastgāh Shur - Rare Samples & Songs Oleg Tsoy.mp3", "title": "Dastgah Shur", "tags": [], "mood": [], "tempo": null, "key": null },
  { "file": "Flamingo - Charles Mingus.mp3", "title": "Flamingo", "tags": [], "mood": [], "tempo": null, "key": null },
  { "file": "Funeral Procession by Ali Jihad Racy - Jonathan van Belle.mp3", "title": "Funeral Procession", "tags": [], "mood": [], "tempo": null, "key": null },
  { "file": "Gendhing Prabu Mataram - Release.mp3", "title": "Gendhing Prabu Mataram", "tags": [], "mood": [], "tempo": null, "key": null },
  { "file": "Guan Pinghu _ Ao_ai  (Fisherman_s song) - Pablo Ángel Zárate Pérez.mp3", "title": "Ao Ai (Fisherman’s Song)", "tags": [], "mood": [], "tempo": null, "key": null },
  { "file": "Guan Pinghu _ Liushui (流水 Flowing Water) - Pablo Ángel Zárate Pérez.mp3", "title": "Liushui (Flowing Water)", "tags": [], "mood": [], "tempo": null, "key": null },

  { "file": "Introduction instrumentale - Cheikh Ahmed Zitouni.mp3", "title": "Introduction instrumentale", "tags": [], "mood": [], "tempo": null, "key": null },
  { "file": "Jaijaivanti - Buddhadev Dasgupta.mp3", "title": "Jaijaivanti", "tags": [], "mood": [], "tempo": null, "key": null },
  { "file": "John Cage - In a Landscape (1948) - Meliton Soupelin’s Score Video Depository.mp3", "title": "In a Landscape", "tags": [], "mood": [], "tempo": null, "key": null },
  { "file": "Ka cham lang (The Raven of the Pagoda) - Tiao Phün Muang.mp3", "title": "Ka Cham Lang", "tags": [], "mood": [], "tempo": null, "key": null },
  { "file": "Kangen (komagaku)  Kitoku - Tokyo Gakuso.mp3", "title": "Kangen", "tags": [], "mood": [], "tempo": null, "key": null },
  { "file": "Kora Boloba - Mamadou Diabaté.mp3", "title": "Kora Boloba", "tags": [], "mood": [], "tempo": null, "key": null },
  { "file": "Kounady la beno - Kandia Kouyaté.mp3", "title": "Kounady la Beno", "tags": [], "mood": [], "tempo": null, "key": null },
  { "file": "Lachrimae pavan by John Dowland  Tuomas Kourula, lute - OPHELIA - Ophelia.mp3", "title": "Lachrimae Pavan", "tags": [], "mood": [], "tempo": null, "key": null },
  { "file": "Marin Marais Livre V - Prélude en harpègement - Barbara Hünninger.mp3", "title": "Prelude en harpegement", "tags": [], "mood": [], "tempo": null, "key": null },
  { "file": "Miles Davis - Blue In Green (Official Audio) - MilesDavisVEVO.mp3", "title": "Blue In Green", "tags": [], "mood": [], "tempo": null, "key": null },
  { "file": "Ornette Coleman - Lonely Woman (1959) - Zaanjam Studios.mp3", "title": "Lonely Woman", "tags": [], "mood": [], "tempo": null, "key": null },
  { "file": "Peking Opera Melody Flowing Water - Release.mp3", "title": "Peking Opera Flowing Water", "tags": [], "mood": [], "tempo": null, "key": null },
  { "file": "Robert de Visée Prélude et Allemande, Jonas Nordberg, theorbo - Jonas Nordberg.mp3", "title": "Prelude & Allemande", "tags": [], "mood": [], "tempo": null, "key": null },
  { "file": "Salih Bilgin   Murat Aydemir   Uşşak Müşterek Taksim 360p - Murat Aydemir.mp3", "title": "Uşşak Müşterek Taksim", "tags": [], "mood": [], "tempo": null, "key": null },
  { "file": "Salih Bilgin   Murat Aydemir   Uşşak Peşrevi Sultan Mahmut - Murat Aydemir.mp3", "title": "Uşşak Peşrev", "tags": [], "mood": [], "tempo": null, "key": null },
  { "file": "Sarama - The Prasit Thawon Ensemble.mp3", "title": "Sarama", "tags": [], "mood": [], "tempo": null, "key": null },
  { "file": "Schumann Abendlied, Op. 85 No. 12 (Arr. Grosvenor) - BGrosvenorVEVO.mp3", "title": "Abendlied", "tags": [], "mood": [], "tempo": null, "key": null },
  { "file": "Simon Shaheen - Bashraf Farahfaza (Turath) - WorldWholeMusic.mp3", "title": "Bashraf Farahfaza", "tags": [], "mood": [], "tempo": null, "key": null },
  { "file": "Solo de violon - Cheikh Ahmed Zitouni.mp3", "title": "Solo de violon", "tags": [], "mood": [], "tempo": null, "key": null },
  { "file": "Tabara - Jali Nyama Suso.mp3", "title": "Tabara", "tags": [], "mood": [], "tempo": null, "key": null },
  { "file": "Tabla Solo - Release.mp3", "title": "Tabla Solo", "tags": [], "mood": [], "tempo": null, "key": null },
  { "file": "Tanovar (Turgun Alimatov) - Gammaldans.mp3", "title": "Tanovar", "tags": [], "mood": [], "tempo": null, "key": null },
  { "file": "The Pinpeat Orchestra Lar Smeur Rou - The Pinpeat Orchestra.mp3", "title": "Lar Smeur Rou", "tags": [], "mood": [], "tempo": null, "key": null },
  { "file": "The Pinpeat Orchestra Trach Toch - The Pinpeat Orchestra.mp3", "title": "Trach Toch", "tags": [], "mood": [], "tempo": null, "key": null },
  { "file": "Turgun Alimatov - buzrug.wmv - Valisher Alimatov.mp3", "title": "Buzrug", "tags": [], "mood": [], "tempo": null, "key": null },
  { "file": "Turgun Alimatov - Nava - Lenus.mp3", "title": "Nava", "tags": [], "mood": [], "tempo": null, "key": null },
  { "file": "فريد الأطرش - تقاسيم استديو الكويت - جودة صوت عالية ومحسنة Farid El Atrache Studio Taqsim Remastered - Farid HQ فريد.mp3", "title": "Farid Al-Atrache Taqsim", "tags": [], "mood": [], "tempo": null, "key": null }
]
